README.md
setup.cfg
setup.py
ashutosh_dist.egg-info/PKG-INFO
ashutosh_dist.egg-info/SOURCES.txt
ashutosh_dist.egg-info/dependency_links.txt
ashutosh_dist.egg-info/not-zip-safe
ashutosh_dist.egg-info/top_level.txt
distributions/Binomialdistribution.py